kmodes/__init__.py
kmodes/kmodes.py
kmodes/kprototypes.py
kmodes/util/__init__.py
kmodes/util/dissim.py
kmodes/util/init_methods.py
kmodes/util/testing.py
kmodes-0.12.2.dist-info/LICENSE
kmodes-0.12.2.dist-info/METADATA
kmodes-0.12.2.dist-info/WHEEL
kmodes-0.12.2.dist-info/top_level.txt
kmodes-0.12.2.dist-info/RECORD
