Metadata-Version: 2.1
Name: kmodes
Version: 0.12.2
Summary: Python implementations of the k-modes and k-prototypes clustering algorithms for clustering categorical data.
Home-page: https://github.com/nicodv/kmodes
Author: Nelis J de Vos
Author-email: njdevos@gmail.com
License: MIT
Platform: UNKNOWN
Classifier: Development Status :: 3 - Alpha
Classifier: Intended Audience :: Science/Research
Classifier: License :: OSI Approved :: MIT License
Classifier: Operating System :: Microsoft :: Windows
Classifier: Operating System :: Unix
Classifier: Operating System :: MacOS
Classifier: Programming Language :: Python
Classifier: Programming Language :: Python :: 3
Classifier: Programming Language :: Python :: 3.6
Classifier: Programming Language :: Python :: 3.7
Classifier: Programming Language :: Python :: 3.8
Classifier: Programming Language :: Python :: 3.9
Classifier: Programming Language :: Python :: 3.10
Classifier: Topic :: Scientific/Engineering
Provides-Extra: dev
License-File: LICENSE
